{
  "@context": "http://iiif.io/api/image/3/context.json",
  "id": "https://sebastiao-lacerda.vercel.app/35103871/ac1b88f858822706a2406af2e35ce397",
  "type": "ImageService3",
  "profile": "level0",
  "protocol": "http://iiif.io/api/image",
  "tiles": [
    {
      "scaleFactors": [
        1,
        2,
        4,
        8,
        16
      ],
      "width": 256
    }
  ],
  "width": 4500,
  "height": 3247,
  "sizes": [
    {
      "width": 300,
      "height": 216
    },
    {
      "width": 1200,
      "height": 866
    }
  ]
}