{
  "@context": "http://iiif.io/api/image/3/context.json",
  "id": "https://sebastiao-lacerda.vercel.app/33514358/ba74f09ede1857eedbcfcd1b891895cc",
  "type": "ImageService3",
  "profile": "level0",
  "protocol": "http://iiif.io/api/image",
  "tiles": [
    {
      "scaleFactors": [
        1,
        2,
        4,
        8,
        16
      ],
      "width": 256
    }
  ],
  "width": 3309,
  "height": 4500,
  "sizes": [
    {
      "width": 220,
      "height": 300
    },
    {
      "width": 1471,
      "height": 2000
    }
  ]
}