{
  "@context": "http://iiif.io/api/image/3/context.json",
  "id": "https://sebastiao-lacerda.vercel.app/33514326/e46e14fc9bc007f52f354b23afb32e9c",
  "type": "ImageService3",
  "profile": "level0",
  "protocol": "http://iiif.io/api/image",
  "tiles": [
    {
      "scaleFactors": [
        1,
        2,
        4,
        8,
        16
      ],
      "width": 256
    }
  ],
  "width": 4500,
  "height": 3244,
  "sizes": [
    {
      "width": 300,
      "height": 216
    },
    {
      "width": 2000,
      "height": 1442
    }
  ]
}